quadrupole/__init__.py
quadrupole/py.typed
quadrupole/quadrupole.py
quadrupole-0.1.7.dist-info/METADATA
quadrupole-0.1.7.dist-info/WHEEL
quadrupole-0.1.7.dist-info/licenses/LICENSE
quadrupole-0.1.7.dist-info/RECORD
