Metadata-Version: 2.4
Name: quadrupole
Version: 0.1.7
Summary: Classes for reading and manipulating molecular quadrupole moments.
Project-URL: Repository, https://github.com/brockdyer03/quadrupole
Author-email: Brock Dyer <brockdyer03@gmail.com>
License-Expression: BSD-3-Clause
License-File: LICENSE
Requires-Python: >=3.12
Requires-Dist: numpy>=2.0.0
